{
    "skipTerminateQuickPick": true,
    "skipSwitchToOutput": false,
    "skipErrorMessage": true,
    "commands": [
      {
        "text": "✪ Build Neko",
        "color": "orange",
        "commandType":"palette",
        "command": "workbench.action.tasks.runTask|Neko",
        "alignment": "right",
        "skipTerminateQuickPick": false,
        "priority": 5
      },
      {
        "text": "(Run)",
        "color": "orange",
        "command": "haxelib run redistHelper -o test -p RedistTest",
        "alignment": "right",
        "skipTerminateQuickPick": false,
        "priority": 4
      },
      {
        "text": "➠ Submit to haxelib",
        "color": "yellow",
        "command": "start haxelib submit .",
        "alignment": "right",
        "skipTerminateQuickPick": false,
        "priority": 0
      }
    ]
  }